pywarp/__init__.py
pywarp/attestation.py
pywarp/backends.py
pywarp/cose.py
pywarp/credentials.py
pywarp/fido/__init__.py
pywarp/fido/metadata.py
pywarp/util/__init__.py
pywarp-0.0.4.dist-info/METADATA
pywarp-0.0.4.dist-info/RECORD
pywarp-0.0.4.dist-info/WHEEL
pywarp-0.0.4.dist-info/top_level.txt
