Metadata-Version: 2.1
Name: pywarp
Version: 0.0.4
Summary: Python WebAuthn Relying Party library
Home-page: https://github.com/pyauth/pywarp
Author: Andrey Kislyuk
Author-email: kislyuk@gmail.com
License: Apache Software License
Platform: UNKNOWN
Classifier: Intended Audience :: Developers
Classifier: License :: OSI Approved :: Apache Software License
Classifier: Operating System :: MacOS :: MacOS X
Classifier: Operating System :: POSIX
Classifier: Programming Language :: Python
Classifier: Programming Language :: Python :: 2.7
Classifier: Programming Language :: Python :: 3.4
Classifier: Programming Language :: Python :: 3.5
Classifier: Programming Language :: Python :: 3.6
Classifier: Programming Language :: Python :: 3.7
Classifier: Topic :: Software Development :: Libraries :: Python Modules
Provides-Extra: test
Requires-Dist: pyjwt (<2,>=1.5.3)
Requires-Dist: cbor2 (<5,>=4.1.2)
Requires-Dist: cryptography (<3,>=2.1.4)
Requires-Dist: requests (<3,>=2.18.4)
Provides-Extra: test
Requires-Dist: coverage; extra == 'test'
Requires-Dist: flake8; extra == 'test'
Requires-Dist: wheel; extra == 'test'
